setup.py
persistpy/__init__.py
persistpy/manipulator.py
persistpy/model.py
persistpy/query.py
persistpy/sequence.py
persistpy/session.py
persistpy/utils.py
persistpy.egg-info/PKG-INFO
persistpy.egg-info/SOURCES.txt
persistpy.egg-info/dependency_links.txt
persistpy.egg-info/not-zip-safe
persistpy.egg-info/requires.txt
persistpy.egg-info/top_level.txt
persistpy/testsuite/__init__.py
persistpy/testsuite/model_test.py