Metadata-Version: 1.0
Name: persistpy
Version: 0.1
Summary: Easy object persistence with MongoDb
Home-page: http://github.com/frascoweb/persistpy
Author: Maxime Bouroumeau-Fuseau
Author-email: maxime.bouroumeau@gmail.com
License: MIT
Platform: any
